pyiron_ontology/__init__.py
pyiron_ontology/_version.py
pyiron_ontology/constructor.py
pyiron_ontology/dynamic.py
pyiron_ontology/parser.py
pyiron_ontology/workflow.py
pyiron_ontology/atomistics/__init__.py
pyiron_ontology/atomistics/constructor.py
pyiron_ontology/atomistics/reasoning.py
pyiron_ontology/example/__init__.py
pyiron_ontology/example/constructor.py
pyiron_ontology-0.2.8.dist-info/LICENSE
pyiron_ontology-0.2.8.dist-info/METADATA
pyiron_ontology-0.2.8.dist-info/WHEEL
pyiron_ontology-0.2.8.dist-info/top_level.txt
pyiron_ontology-0.2.8.dist-info/RECORD
