Metadata-Version: 2.2
Name: pyiron_ontology
Version: 0.2.8
Summary: pyiron_ontology - module extension to pyiron.
Author-email: Liam Huber <liamhuber@greyhavensolutions.com>
License: BSD 3-Clause License
Project-URL: Homepage, https://github.com/pyiron/pyiron_ontology
Project-URL: Documentation, https://pyiron-ontology.readthedocs.io
Project-URL: Repository, https://github.com/pyiron/pyiron_ontology
Keywords: pyiron
Classifier: Development Status :: 5 - Production/Stable
Classifier: Topic :: Scientific/Engineering :: Physics
Classifier: License :: OSI Approved :: BSD License
Classifier: Intended Audience :: Science/Research
Classifier: Operating System :: OS Independent
Classifier: Programming Language :: Python :: 3.9
Classifier: Programming Language :: Python :: 3.10
Classifier: Programming Language :: Python :: 3.11
Classifier: Programming Language :: Python :: 3.12
Requires-Python: <3.13,>=3.9
License-File: LICENSE
Requires-Dist: numpy<1.27.0,>=1.26.3
Requires-Dist: owlready2<=0.47,>=0.46
Requires-Dist: pandas<2.3.0,>=2.2.0
Requires-Dist: pint<=0.24.4,>=0.24
